{"nodes":[{"id":"n0","name":"Module","x":394,"y":-294,"data":{"name":"double"}},{"id":"n1","name":"Number","x":71,"y":-285,"data":{"val":5}},{"id":"n2","name":"Log","x":770,"y":-303,"data":{"val":""}},{"id":"n3","name":"EngineReady","x":9,"y":-572,"data":{}},{"id":"n4","name":"Sequence","x":517,"y":-612,"data":{"val":2}},{"id":"n5","name":"Log","x":866,"y":-611,"data":{"val":"123"}}],"connections":[{"source":"n1","sourceOutput":"out","target":"n0","targetInput":"число"},{"source":"n0","sourceOutput":"x2","target":"n2","targetInput":"data"},{"source":"n4","sourceOutput":"out1","target":"n5","targetInput":"in"},{"source":"n3","sourceOutput":"out","target":"n4","targetInput":"in"},{"source":"n4","sourceOutput":"out2","target":"n2","targetInput":"in"}],"comments":[]}